{
  "sections": {
    "d728499e-6c83-4b7c-90c0-2eda0378a3a4": {
      "type": "contact-info",
      "settings": {
        "contact_page_title": "Kontakty",
        "contact_page_companyname": "ILUMIX light s.r.o.",
        "contact_page_address": "Holečkova 368\/4 <br>\nKarlovy Vary <br>\nČeská republika",
        "contact_page_companyinfo": "IČO: 29115728 <br>\nDIČ: CZ29115728 <br> <br>\nČSOB: 4377999\/0300 <br>\nRB: 333888999\/5500 <br>\nSpisová značka: C 25969 vedená u Krajského soudu v Plzni.",
        "contact_page_phone": "+420 774 109 102",
        "contact_page_email": "info@360design.cz"
      }
    },
    "ea5f593d-e910-4744-ac79-7ce9c5de9fd9": {
      "type": "our-team",
      "blocks": {
        "93bbdb45-2a2c-4231-9b69-8c3d848ad63a": {
          "type": "our-vision",
          "settings": {
            "member_name": "Michal Oláh",
            "member_position": "Vedoucí projektů",
            "member_phone": "+420 773 900 590",
            "member_mail": "m.olah@ilumix.cz"
          }
        },
        "6de61e8a-e1c7-4924-a038-6c2387e21d02": {
          "type": "our-vision",
          "settings": {
            "member_name": "Richard Šimůnek",
            "member_position": "Projektový manažer",
            "member_phone": "+420 775 672 230",
            "member_mail": "simunek@ilumix.cz"
          }
        },
        "9823b1b4-f916-4d96-8cf2-968c20d9db4e": {
          "type": "our-vision",
          "settings": {
            "member_name": "Pavel Huml",
            "member_position": "Projektový manažer",
            "member_phone": "+420 602 120 666",
            "member_mail": "huml@ilumix.cz"
          }
        },
        "1d9d54d0-4130-4fa4-9553-c388d09e39ed": {
          "type": "our-vision",
          "settings": {
            "member_name": "Libor Jára",
            "member_position": "Vedoucí pobočky KV",
            "member_phone": "+420 773 900 507",
            "member_mail": "info@ilumix.cz"
          }
        },
        "018479ef-9c98-41b3-bfda-9f60122099f4": {
          "type": "our-vision",
          "settings": {
            "member_name": "Martin Jaroš",
            "member_position": "Administrace",
            "member_phone": "",
            "member_mail": "jaros@ilumix.cz"
          }
        },
        "96489f55-2002-434d-987e-c2dac4fa77cf": {
          "type": "our-vision",
          "settings": {
            "member_name": "David Helebrant",
            "member_position": "Jednatel společnosti",
            "member_phone": "+420 774 109 102",
            "member_mail": "helebrant@ilumix.cz"
          }
        }
      },
      "block_order": [
        "93bbdb45-2a2c-4231-9b69-8c3d848ad63a",
        "6de61e8a-e1c7-4924-a038-6c2387e21d02",
        "9823b1b4-f916-4d96-8cf2-968c20d9db4e",
        "1d9d54d0-4130-4fa4-9553-c388d09e39ed",
        "018479ef-9c98-41b3-bfda-9f60122099f4",
        "96489f55-2002-434d-987e-c2dac4fa77cf"
      ],
      "settings": {
        "section_padding_top": 100,
        "section_padding_bottom": 100,
        "section_padding_top_lg": 60,
        "section_padding_bottom_lg": 60,
        "section_padding_top_xs": 40,
        "section_padding_bottom_xs": 40,
        "our_team_title": "Náš tým"
      }
    },
    "626de182-dc50-4f58-8433-ddaf51ce2059": {
      "type": "form-contact",
      "settings": {
        "contact_us_padding_top": 60,
        "contact_us_padding_bottom": 60,
        "contact_us_padding_top_ipad": 30,
        "contact_us_padding_bottom_ipad": 30,
        "contact_us_padding_top_xs": 20,
        "contact_us_padding_bottom_xs": 20,
        "section_bg_color": "#f6f6f6",
        "section_title": "Napište nám a rozsvítíme to společně",
        "section_des": "Obratem zodpovíme veškeré vaše otázky i zpracujeme cenovou nabídku.",
        "name_placeholder": "Jméno",
        "email_placeholder": "E-mail",
        "phone_placeholder": "Telefon",
        "message_placeholder": "Zpráva",
        "form_button_name": "Odeslat",
        "read_agree_text": "Souhlasím se zpracováním osobních údajů"
      }
    }
  },
  "order": [
    "d728499e-6c83-4b7c-90c0-2eda0378a3a4",
    "ea5f593d-e910-4744-ac79-7ce9c5de9fd9",
    "626de182-dc50-4f58-8433-ddaf51ce2059"
  ]
}
